Metadata-Version: 2.1
Name: toolbox-aazerra
Version: 0.0.1
Summary: Personal utility functions
Home-page: https://github.com/aazerra/toolbox-py
Maintainer: Alireza Rabie
Maintainer-email: alirezarabie793@gmail.com
License: MIT
Keywords: utils,utility,functions
Classifier: Programming Language :: Python :: 3
License-File: LICENSE
